LICENSE
MANIFEST.in
README.rst
README.txt
README.wiki
ez_setup.py
setup.py
mongokit/__init__.py
mongokit/pylons/__init__.py
mongokit/pylons/auth.py
mongokit/pylons/document.py
mongokit/pylons/generators.py
mongokit/pylons/mongo_exceptions.py
mongokit/pylons/pylons_env.py
mongokit_pylons.egg-info/PKG-INFO
mongokit_pylons.egg-info/SOURCES.txt
mongokit_pylons.egg-info/dependency_links.txt
mongokit_pylons.egg-info/not-zip-safe
mongokit_pylons.egg-info/requires.txt
mongokit_pylons.egg-info/top_level.txt
tests/test_api.py
tests/test_auth.py
tests/test_descriptors.py
tests/test_inheritance.py
tests/test_structure.py
tests/test_types.py