Metadata-Version: 1.0
Name: mongokit-pylons
Version: 0.2.0
Summary: MongoDB interface for ORM-like object mapping (w/ Pylons support)
Home-page: http://bitbucket.org/bwmcadams/mongokit-pylons/
Author: Brendan W. McAdams
Author-email: bwmcadams@gmail.com
License: New BSD License
Keywords: mongo mongodb mongokit pylons
Platform: UNKNOWN
Classifier: Development Status :: 4 - Beta
Classifier: Environment :: Other Environment
Classifier: Environment :: Web Environment
Classifier: Intended Audience :: Developers
Classifier: License :: OSI Approved :: BSD License
Classifier: Operating System :: OS Independent
Classifier: Programming Language :: Python
Classifier: Topic :: Database
Classifier: Topic :: Utilities
Classifier: Topic :: Software Development :: Libraries :: Python Modules
